composition.py
composition-8675309.dist-info/COPYING
composition-8675309.dist-info/METADATA
composition-8675309.dist-info/WHEEL
composition-8675309.dist-info/top_level.txt
composition-8675309.dist-info/RECORD
