Metadata-Version: 2.1
Name: composition
Version: 8675309
Summary: What You Crave
Home-page: https://github.com/Julian/composition
Author: Julian Berman
Author-email: Julian+ButDontSendMeEmailsAboutThisOne@GrayVines.com
License: UNKNOWN
Project-URL: Source, https://github.com/Julian/composition
Project-URL: Issues, https://github.com/Julian/composition/issues/
Platform: UNKNOWN
Classifier: Development Status :: 6 - Mature
Classifier: Operating System :: OS Independent
Classifier: Programming Language :: Python
Classifier: License :: OSI Approved :: MIT License
Classifier: Programming Language :: Python :: 3.6
Classifier: Programming Language :: Python :: 3.7
Classifier: Programming Language :: Python :: 3.8
Classifier: Programming Language :: Python :: 3
Classifier: Programming Language :: Python :: Implementation :: CPython
Requires-Dist: forbiddenfruit (!=0.1.3)
